Metadata-Version: 2.1
Name: junkaptor
Version: 0.0.5
Summary: Module package for sanitizing data
Home-page: https://code.stroeder.com/pymod/python-junkaptor
Download-URL: https://pypi.python.org/pypi/junkaptor/
Author: Michael Stroeder
Author-email: michael@stroeder.com
Maintainer: Michael Stroeder
Maintainer-email: michael@stroeder.com
License: Apache-2.0
Project-URL: Code, https://code.stroeder.com/pymod/python-junkaptor
Project-URL: Issue tracker, https://code.stroeder.com/pymod/python-junkaptor/issues
Classifier: Development Status :: 5 - Production/Stable
Classifier: Intended Audience :: Developers
Classifier: Intended Audience :: Information Technology
Classifier: Intended Audience :: System Administrators
Classifier: License :: OSI Approved :: Apache Software License
Classifier: Programming Language :: Python
Classifier: Programming Language :: Python :: 3
Classifier: Programming Language :: Python :: 3.6
Classifier: Programming Language :: Python :: 3.7
Classifier: Programming Language :: Python :: 3.8
Classifier: Programming Language :: Python :: 3.9
Classifier: Programming Language :: Python :: 3.10
Classifier: Programming Language :: Python :: 3 :: Only
Classifier: Topic :: Software Development :: Libraries :: Python Modules
Requires-Python: >=3.6
License-File: LICENSE
